{
    "b00001213_21i6bq_20150306_174403e.jpg": {
        "minute_id": "20150306_1744",
        "utc_time": "UTC_2015-03-06_17:44",
        "atributtes": [
            "enclosed area",
            "no horizon",
            "man-made",
            "indoor lighting",
            "cloth",
            "socializing",
            "wood",
            "eating",
            "congregating",
            "glossy"
        ],
        "categories": {
            "beer_hall": 0.364,
            "pub/indoor": 0.079,
            "coffee_shop": 0.061,
            "beauty_salon": 0.045,
            "sushi_bar": 0.042
        },
        "concepts": {
            "person": {
                "score": 0.992006719,
                "box": [
                    168.4970703125,
                    8.310383952353613,
                    591.3922164351852,
                    475.0022383760815
                ]
            },
            "chair": {
                "score": 0.838109851,
                "box": [
                    557.8857542438271,
                    378.93291772889694,
                    971.249324845679,
                    760.0799380846261
                ]
            }
        },
        "local_time": "2015-03-06_17:44",
        "timezone": "Europe/London",
        "latitude": 53.37849021819483,
        "longitude": -1.462383270263672,
        "activity": "NULL",
        "location": "Sheffield Tap",
        "elevation": "NULL",
        "speed": "NULL",
        "heart": "NULL",
        "calories": "1.2032999992370603",
        "steps": "NULL"
    },
    "b00001214_21i6bq_20150306_174437e.jpg": {
        "minute_id": "20150306_1744",
        "utc_time": "UTC_2015-03-06_17:44",
        "atributtes": [
            "enclosed area",
            "no horizon",
            "man-made",
            "indoor lighting",
            "socializing",
            "cloth",
            "wood",
            "glass",
            "congregating",
            "eating"
        ],
        "categories": {
            "airplane_cabin": 0.299,
            "beer_hall": 0.155,
            "pub/indoor": 0.027,
            "beauty_salon": 0.024,
            "fastfood_restaurant": 0.023
        },
        "concepts": {
            "chair": {
                "score": 0.992335618,
                "box": [
                    516.8921682098766,
                    314.77046462129954,
                    895.1713927469136,
                    765.0
                ]
            },
            "person": {
                "score": 0.730060816,
                "box": [
                    952.4135802469136,
                    272.58031025405757,
                    1002.5721450617284,
                    336.6033147386283
                ]
            }
        },
        "local_time": "2015-03-06_17:44",
        "timezone": "Europe/London",
        "latitude": 53.37849021819483,
        "longitude": -1.462383270263672,
        "activity": "NULL",
        "location": "Sheffield Tap",
        "elevation": "NULL",
        "speed": "NULL",
        "heart": "NULL",
        "calories": "1.2032999992370603",
        "steps": "NULL"
    },
    "b00001215_21i6bq_20150306_174513e.jpg": {
        "minute_id": "20150306_1745",
        "utc_time": "UTC_2015-03-06_17:45",
        "atributtes": [
            "enclosed area",
            "no horizon",
            "man-made",
            "indoor lighting",
            "cloth",
            "wood",
            "socializing",
            "glass",
            "glossy",
            "eating"
        ],
        "categories": {
            "airplane_cabin": 0.352,
            "train_interior": 0.097,
            "beer_hall": 0.073,
            "bus_interior": 0.061,
            "beauty_salon": 0.026
        },
        "concepts": {
            "chair": {
                "score": 0.721582234,
                "box": [
                    909.0657793209876,
                    378.90303588110555,
                    995.8336226851852,
                    634.882375859032
                ]
            },
            "person": {
                "score": 0.930387914,
                "box": [
                    903.7246334876543,
                    131.5401592727535,
                    1021.0672260802469,
                    256.99131926229177
                ]
            }
        },
        "local_time": "2015-03-06_17:45",
        "timezone": "Europe/London",
        "latitude": 53.37849021819483,
        "longitude": -1.462383270263672,
        "activity": "NULL",
        "location": "Sheffield Tap",
        "elevation": "NULL",
        "speed": "NULL",
        "heart": "NULL",
        "calories": "1.2032999992370603",
        "steps": "NULL"
    },
    "b00001216_21i6bq_20150306_174552e.jpg": {
        "minute_id": "20150306_1745",
        "utc_time": "UTC_2015-03-06_17:45",
        "atributtes": [
            "no horizon",
            "enclosed area",
            "man-made",
            "indoor lighting",
            "cloth",
            "glossy",
            "wood",
            "working",
            "socializing",
            "metal"
        ],
        "categories": {
            "airplane_cabin": 0.374,
            "beer_hall": 0.04,
            "beauty_salon": 0.038,
            "television_studio": 0.029,
            "car_interior": 0.019
        },
        "concepts": {
            "chair": {
                "score": 0.703394949,
                "box": [
                    36.73681339216821,
                    42.99419072048723,
                    631.5409915123457,
                    741.6581527457749
                ]
            },
            "person": {
                "score": 0.794684172,
                "box": [
                    311.81059510030866,
                    72.7682021826752,
                    363.48975212191357,
                    174.4691718708385
                ]
            }
        },
        "local_time": "2015-03-06_17:45",
        "timezone": "Europe/London",
        "latitude": 53.37849021819483,
        "longitude": -1.462383270263672,
        "activity": "NULL",
        "location": "Sheffield Tap",
        "elevation": "NULL",
        "speed": "NULL",
        "heart": "NULL",
        "calories": "1.2032999992370603",
        "steps": "NULL"
    },
    "b00001217_21i6bq_20150306_174713e.jpg": {
        "minute_id": "20150306_1747",
        "utc_time": "UTC_2015-03-06_17:47",
        "atributtes": [
            "enclosed area",
            "no horizon",
            "man-made",
            "indoor lighting",
            "cloth",
            "wood",
            "socializing",
            "glass",
            "congregating",
            "eating"
        ],
        "categories": {
            "airplane_cabin": 0.115,
            "beer_hall": 0.105,
            "beauty_salon": 0.084,
            "train_interior": 0.048,
            "fastfood_restaurant": 0.033
        },
        "concepts": {
            "chair": {
                "score": 0.765955687,
                "box": [
                    788.1949266975308,
                    718.4938601028821,
                    972.418499228395,
                    763.9250734817883
                ]
            },
            "person": {
                "score": 0.814750433,
                "box": [
                    840.0534336419753,
                    177.2435651731885,
                    995.0659722222222,
                    498.9292778456507
                ]
            },
            "cup": {
                "score": 0.776341379,
                "box": [
                    913.7949459876543,
                    290.2531440987075,
                    934.1601080246913,
                    328.6991198200825
                ]
            }
        },
        "local_time": "2015-03-06_17:47",
        "timezone": "Europe/London",
        "latitude": 53.37849021819483,
        "longitude": -1.462383270263672,
        "activity": "NULL",
        "location": "Sheffield Tap",
        "elevation": "NULL",
        "speed": "NULL",
        "heart": "NULL",
        "calories": "1.2032999992370603",
        "steps": "NULL"
    },
    "b00001218_21i6bq_20150306_174751e.jpg": {
        "minute_id": "20150306_1747",
        "utc_time": "UTC_2015-03-06_17:47",
        "atributtes": [
            "no horizon",
            "enclosed area",
            "man-made",
            "indoor lighting",
            "cloth",
            "socializing",
            "working",
            "waiting in line",
            "eating",
            "stressful"
        ],
        "categories": {
            "discotheque": 0.124,
            "beer_hall": 0.103,
            "airplane_cabin": 0.1,
            "beauty_salon": 0.099,
            "dressing_room": 0.034
        },
        "concepts": {
            "person": {
                "score": 0.718800545,
                "box": [
                    0.5784897509916329,
                    265.0780852767062,
                    392.4816261574074,
                    756.4620397898777
                ]
            }
        },
        "local_time": "2015-03-06_17:47",
        "timezone": "Europe/London",
        "latitude": 53.37849021819483,
        "longitude": -1.462383270263672,
        "activity": "NULL",
        "location": "Sheffield Tap",
        "elevation": "NULL",
        "speed": "NULL",
        "heart": "NULL",
        "calories": "1.2032999992370603",
        "steps": "NULL"
    },
    "b00001219_21i6bq_20150306_174822e.jpg": {
        "minute_id": "20150306_1748",
        "utc_time": "UTC_2015-03-06_17:48",
        "atributtes": [
            "enclosed area",
            "no horizon",
            "man-made",
            "indoor lighting",
            "wood",
            "cloth",
            "socializing",
            "glass",
            "eating",
            "working"
        ],
        "categories": {
            "beer_hall": 0.136,
            "airplane_cabin": 0.063,
            "beauty_salon": 0.045,
            "church/indoor": 0.04,
            "fastfood_restaurant": 0.031
        },
        "concepts": {
            "chair": {
                "score": 0.986758769,
                "box": [
                    518.8387345679013,
                    338.8864663809784,
                    970.2598379629629,
                    761.8700995327027
                ]
            },
            "person": {
                "score": 0.762852132,
                "box": [
                    27.83542209201389,
                    159.9565424012744,
                    480.11275077160496,
                    758.1840445778587
                ]
            }
        },
        "local_time": "2015-03-06_17:48",
        "timezone": "Europe/London",
        "latitude": 53.37849021819483,
        "longitude": -1.462383270263672,
        "activity": "NULL",
        "location": "Sheffield Tap",
        "elevation": "NULL",
        "speed": "NULL",
        "heart": "NULL",
        "calories": "1.2032999992370603",
        "steps": "NULL"
    }
}